[{"email":"Cloe.Atzeni0@hotmail.com","fullname":"Viviano Marchi","isTutor":true,"reviews":[{"stars":0,"text":"Consequatur nam quo eligendi nesciunt ut et iusto cum.","tutorId":"62c2b0e14e4776e6255b8dad","_id":"62c2b0e14e4776e6255b8db1","__v":0},{"stars":0,"text":"In illo nihil iusto impedit molestiae.","tutorId":"62c2b0e14e4776e6255b8dad","_id":"62c2b0e14e4776e6255b8db5","__v":0}],"createdReviews":[],"bookedSessions":[],"requestedSessions":[],"subjects":["Science","Maths","Physics"],"bio":"Numquam iusto ut explicabo ullam soluta nihil odio.","location":"est error","avatar":"https://cloudflare-ipfs.com/ipfs/Qmd3W5DuhgHirLHGVixi6V76LhCkZUz6pnFt5AJBiyvHye/avatar/802.jpg","coordinates":[12.2191,46.4904],"_id":"62c2b0e14e4776e6255b8dad","__v":1},{"email":"Adina69@yahoo.com","fullname":"Calpurnia Violante","isTutor":false,"reviews":[],"createdReviews":[{"stars":0,"text":"Consequatur nam quo eligendi nesciunt ut et iusto cum.","tutorId":"62c2b0e14e4776e6255b8dad","_id":"62c2b0e14e4776e6255b8db1","__v":0},{"stars":0,"text":"In illo nihil iusto impedit molestiae.","tutorId":"62c2b0e14e4776e6255b8dad","_id":"62c2b0e14e4776e6255b8db5","__v":0}],"bookedSessions":[],"requestedSessions":[],"subjects":[],"bio":"","location":"","avatar":"https://cloudflare-ipfs.com/ipfs/Qmd3W5DuhgHirLHGVixi6V76LhCkZUz6pnFt5AJBiyvHye/avatar/403.jpg","coordinates":[],"_id":"62c2b0e14e4776e6255b8db0","__v":0}]